PyDMX_Drivers_FTDI-0.1.0-py3.9-nspkg.pth
dmx_drivers/ftdi/__init__.py
dmx_drivers/ftdi/ft232r.py
PyDMX_Drivers_FTDI-0.1.0.dist-info/LICENSE
PyDMX_Drivers_FTDI-0.1.0.dist-info/METADATA
PyDMX_Drivers_FTDI-0.1.0.dist-info/WHEEL
PyDMX_Drivers_FTDI-0.1.0.dist-info/namespace_packages.txt
PyDMX_Drivers_FTDI-0.1.0.dist-info/top_level.txt
PyDMX_Drivers_FTDI-0.1.0.dist-info/RECORD
