Metadata-Version: 2.1
Name: PyDMX-Drivers-FTDI
Version: 0.1.0
Summary: Device drivers for PyDMX for FTDI-based devices. Not affiliated with FTDI.
Author-email: Jacob Allen <jacob@polyomino.xyz>
License: BSD-3-Clause
Project-URL: Homepage, https://github.com/JMAlego/PyDMX
Project-URL: Bug Tracker, https://github.com/JMAlego/PyDMX/issues
Classifier: Programming Language :: Python :: 3
Classifier: License :: OSI Approved :: BSD License
Classifier: Operating System :: Microsoft :: Windows
Classifier: Operating System :: POSIX :: Linux
Requires-Python: >=3.7
License-File: LICENSE
Requires-Dist: pylibftdi (>=0.18.1)
Requires-Dist: pydmx (>=0.1.0)
